[
    {
        "tag": "p",
        "class": "marg",
        "html": "<a data-id=\"forarbeid/prop-129-l-201516\" class=\" reference\" href=\"/forarbeid/prop-129-l-201516\">Prop.129 L (2015–2016)</a>, <a data-id=\"forarbeid/inns-41-l-201617\" class=\" reference\" href=\"/forarbeid/inns-41-l-201617\">Innst.41 L (2016–2017)</a>, <a data-id=\"forarbeid/lovvedtak-11-201617\" class=\" reference\" href=\"/forarbeid/lovvedtak-11-201617\">Lovvedtak 11 (2016–2017)</a>. Stortingets første og andre gangs behandling hhv. 29. november og 6. desember 2016. Fremmet av Samferdselsdepartementet.",
        "text": "Prop.129 L (2015–2016), Innst.41 L (2016–2017), Lovvedtak 11 (2016–2017). Stortingets første og andre gangs behandling hhv. 29. november og 6. desember 2016. Fremmet av Samferdselsdepartementet."
    },
    {
        "tag": "p",
        "class": "marg",
        "html": "Endringer i følgende lover:",
        "text": "Endringer i følgende lover:"
    },
    {
        "tag": "table",
        "class": "listeItem avsnitt",
        "html": "<tr>\n<td data-level=\"1\" class=\"morTag_nf small leftMargin_1 listeitemNummer morTableVerticalAlignTop morTableAlignRight morTableWidthPercent5\">1\t</td>\n<td class=\" morTableVerticalAlignTop morTableAlignLeft\">\n<a data-id=\"lov/1999-07-16-69\" class=\" reference\" href=\"/lov/1999-07-16-69\">Lov 16. juli 1999 nr. 69</a> om offentlige anskaffelser.</td>\n</tr>",
        "text": "1\tLov 16. juli 1999 nr. 69 om offentlige anskaffelser."
    },
    {
        "tag": "table",
        "class": "listeItem avsnitt",
        "html": "<tr>\n<td data-level=\"1\" class=\"morTag_nf small leftMargin_1 listeitemNummer morTableVerticalAlignTop morTableAlignRight morTableWidthPercent5\">2\t</td>\n<td class=\" morTableVerticalAlignTop morTableAlignLeft\">\n<a data-id=\"lov/2002-06-21-45\" class=\" reference\" href=\"/lov/2002-06-21-45\">Lov 21. juni 2002 nr. 45</a> om yrkestransport med motorvogn og fartøy (yrkestransportlova).</td>\n</tr>",
        "text": "2\tLov 21. juni 2002 nr. 45 om yrkestransport med motorvogn og fartøy (yrkestransportlova)."
    },
    {
        "tag": "h2",
        "class": "",
        "html": "I",
        "text": "I"
    },
    {
        "tag": "p",
        "class": "avsnitt",
        "html": "I <a data-id=\"lov/1999-07-16-69\" class=\" reference\" href=\"/lov/1999-07-16-69\">lov 16. juli 1999 nr. 69</a> om offentlige anskaffelser gjøres følgende endring.",
        "text": "I lov 16. juli 1999 nr. 69 om offentlige anskaffelser gjøres følgende endring."
    },
    {
        "tag": "p",
        "class": "marg",
        "html": "§ 16 annet ledd skal lyde:",
        "text": "§ 16 annet ledd skal lyde:"
    },
    {
        "tag": "p",
        "class": "avsnitt",
        "html": "Departementet kan gi forskrift om at oppdragsgiver skal stille nærmere bestemte energi- og miljøkrav som har sitt utspring i EØS-avtalen, WTO-avtalen om offentlige innkjøp eller andre internasjonale avtaler som Norge er forpliktet av.",
        "text": "Departementet kan gi forskrift om at oppdragsgiver skal stille nærmere bestemte energi- og miljøkrav som har sitt utspring i EØS-avtalen, WTO-avtalen om offentlige innkjøp eller andre internasjonale avtaler som Norge er forpliktet av."
    },
    {
        "tag": "h2",
        "class": "",
        "html": "II",
        "text": "II"
    },
    {
        "tag": "p",
        "class": "avsnitt",
        "html": "I <a data-id=\"lov/2002-06-21-45\" class=\" reference\" href=\"/lov/2002-06-21-45\">lov 21. juni 2002 nr. 45</a> om yrkestransport med motorvogn og fartøy gjøres følgende endring:",
        "text": "I lov 21. juni 2002 nr. 45 om yrkestransport med motorvogn og fartøy gjøres følgende endring:"
    },
    {
        "tag": "p",
        "class": "marg",
        "html": "Ny <a data-id=\"lov/2002-06-21-45/§11a\" class=\" reference\" href=\"/lov/2002-06-21-45/%C2%A711a\">§ 11a</a> skal lyde:",
        "text": "Ny § 11a skal lyde:"
    },
    {
        "tag": "p",
        "class": "avsnitt",
        "html": "Departementet kan i forskrift fastsetje at den som har løyve for persontransport etter lova her, eller løyvefritak, og som får godtgjersle eller einerett for å utføre offentleg teneste, skal stille nærare fastsette energi- og miljøkrav ved kjøp av kjøretøy. Kravet gjeld for kjøretøy som vert nytta ved levering av den offentlege tenesta.",
        "text": "Departementet kan i forskrift fastsetje at den som har løyve for persontransport etter lova her, eller løyvefritak, og som får godtgjersle eller einerett for å utføre offentleg teneste, skal stille nærare fastsette energi- og miljøkrav ved kjøp av kjøretøy. Kravet gjeld for kjøretøy som vert nytta ved levering av den offentlege tenesta."
    },
    {
        "tag": "h2",
        "class": "",
        "html": "III",
        "text": "III"
    },
    {
        "tag": "p",
        "class": "avsnitt",
        "html": "Loven gjelder fra den tid Kongen bestemmer.",
        "text": "Loven gjelder fra den tid Kongen bestemmer."
    }
]