<?xml version="1.0" encoding="UTF-8"?>
<dokument xmlns:xsi="http://www.w3.org/2001/XMLSchema-instance" xmlns="https://lovdata.no/regelverk" xsi:schemaLocation="lov-eksempel.xsd" id="for-2018-05-24-761" type="lt" url="https://lovdata.no/lovtidend/forskrift/2018-05-24-761">
  <metadata>
    <type>lt</type>
    <base>LT</base>
    <id>LT/lt/2018-05-24-761</id>
    <dato>24.05.2018 nr. 761</dato>
    <dato type="iso">2018-05-24</dato>
    <ikraft>24.05.2018</ikraft>
    <ikraft type="iso">2018-05-24</ikraft>
    <departement>Nærings- og fiskeridepartementet</departement>
    <etat/>
    <gjelder>Norge</gjelder>
    <hjemmel><ref id="lov-2008-06-06-37-§16">L06.06.2008 nr. 37 § 16</ref>, <ref id="lov-2008-06-06-37-§36">§ 36</ref></hjemmel>
    <endrer type="ref">https://lovdata.no/for/2014-12-19-1836</endrer>
    <rettet/>
    <journalnummer>2018-0435</journalnummer>
  </metadata>
  <tekst>
    <korttittel>Endr. i forskrift om forbud mot fangst av snøkrabbe</korttittel>
    <tittel>Forskrift om endring i forskrift om forbud mot fangst av snøkrabbe</tittel>
    <marg niv="1" id="/marg/1"><b>Hjemmel:</b> Fastsatt av Nærings- og fiskeridepartementet 24. mai 2018 med hjemmel i lov 6. juni 2008 nr. 37 om forvaltning av viltlevande marine ressursar (havressurslova) § 16 og § 36.</marg>
    <kapittel type="kapittel" id="/kapittel/i" url="https://lovdata.no/lovtidend/forskrift/2018-05-24-761/ki">
      <kverdi>I</kverdi>
      <ktittel/>
      <ledd id="/kapittel/i/ledd/1">I forskrift 19. desember 2014 nr. 1836 om forbud mot fangst av snøkrabbe gjøres følgende endringer:
<br/></ledd>
      <ledd id="/kapittel/i/ledd/2">§ 4 skal lyde:</ledd>
      <ledd id="/kapittel/i/ledd/3">§ 4. <i>Forbud mot fangst i visse perioder og innblanding av bløtkrabbe</i></ledd>
      <ledd id="/kapittel/i/ledd/4">I perioden fra og med 15. juni til og med 15. september er det forbudt å fangste snøkrabbe.</ledd>
      <ledd id="/kapittel/i/ledd/5">Det er ikke tillatt å ha mer enn 20 % innblanding av bløtkrabbe i fangst etter snøkrabbe. Ved mer enn 20 % innblanding av bløtkrabbe i de enkelte fangster, skal fangsting stoppes og fartøyet skal skifte fangstfelt.</ledd>
      <ledd id="/kapittel/i/ledd/6">Fartøy som fangster snøkrabbe skal rapportere om innblanding av bløtkrabbe i fangstene på e-post til
<lenke url="https://lovdata.no/static/mailto: fmc@fiskeridir.no">fmc@fiskeridir.no</lenke> i henhold til gjeldende retningslinjer for rapportering om innblanding av bløtkrabbe fastsatt av Fiskeridirektoratet.</ledd>
      <ledd id="/kapittel/i/ledd/7">Fiskeridirektoratet kan forby fangst av snøkrabbe i perioder og områder dersom biologiske hensyn tilsier det.
<br/></ledd>
      <ledd id="/kapittel/i/ledd/8">Ny § 5 skal lyde:</ledd>
      <ledd id="/kapittel/i/ledd/9">§ 5. <i>Melding om oppstart av fangst</i></ledd>
      <ledd id="/kapittel/i/ledd/10">Fartøy som skal fangste snøkrabbe skal senest en uke før fangststart, sende melding til Fiskeridirektoratet om når fangsten planlegges påbegynt. Melding sendes til Fiskeridirektoratets sjøtjeneste på e-post
<lenke url="https://lovdata.no/static/mailto: rojen@fiskeridir.no"> rojen@fiskeridir.no</lenke> og
<lenke url="https://lovdata.no/static/mailto: chval@fiskeridir.no">chval@fiskeridir.no</lenke>
<br/>
<marg niv="1" id="/kapittel/i/ledd/10/marg/1">Gjeldende § 5 - § 8 blir § 6 - § 9.</marg></ledd>
    </kapittel>
    <kapittel type="kapittel" id="/kapittel/ii" url="https://lovdata.no/lovtidend/forskrift/2018-05-24-761/kii">
      <kverdi>II</kverdi>
      <ktittel/>
      <ledd id="/kapittel/ii/ledd/1">Forskriften trer i kraft straks.</ledd>
    </kapittel>
  </tekst>
</dokument>
