[
    {
        "tag": "p",
        "class": "marg",
        "html": "<a data-id=\"forarbeid/prop-136-ls-202021\" class=\" reference\" href=\"/forarbeid/prop-136-ls-202021\">Prop.136 LS (2020–2021)</a>, <a data-id=\"forarbeid/inns-597-l-202021\" class=\" reference\" href=\"/forarbeid/inns-597-l-202021\">Innst.597 L (2020–2021)</a>, <a data-id=\"forarbeid/lovvedtak-157-202021\" class=\" reference\" href=\"/forarbeid/lovvedtak-157-202021\">Lovvedtak 157 (2020–2021)</a>. Stortingets første og andre gangs behandling hhv. 4. og 7. juni 2021. Fremmet av Nærings- og fiskeridepartementet.",
        "text": "Prop.136 LS (2020–2021), Innst.597 L (2020–2021), Lovvedtak 157 (2020–2021). Stortingets første og andre gangs behandling hhv. 4. og 7. juni 2021. Fremmet av Nærings- og fiskeridepartementet."
    },
    {
        "tag": "p",
        "class": "avsnitt",
        "html": "Endringer i følgende lover:",
        "text": "Endringer i følgende lover:"
    },
    {
        "tag": "table",
        "class": "listeItem avsnitt",
        "html": "<tr><td data-level=\"1\" class=\"morTag_nf small leftMargin_1 listeitemNummer morTableVerticalAlignTop morTableAlignRight morTableWidthPercent5\">1\t</td><td class=\" morTableVerticalAlignTop morTableAlignLeft\"><a data-id=\"lov/1997-06-13-44\" class=\" reference\" href=\"/lov/1997-06-13-44\">Lov 13. juni 1997 nr. 44 om aksjeselskaper (aksjeloven)</a>.</td></tr>",
        "text": "1\tLov 13. juni 1997 nr. 44 om aksjeselskaper (aksjeloven)."
    },
    {
        "tag": "table",
        "class": "listeItem avsnitt",
        "html": "<tr><td data-level=\"1\" class=\"morTag_nf small leftMargin_1 listeitemNummer morTableVerticalAlignTop morTableAlignRight morTableWidthPercent5\">2\t</td><td class=\" morTableVerticalAlignTop morTableAlignLeft\"><a data-id=\"lov/1997-06-13-45\" class=\" reference\" href=\"/lov/1997-06-13-45\">Lov 13. juni 1997 nr. 45 om allmennaksjeselskaper (allmennaksjeloven)</a>.</td></tr>",
        "text": "2\tLov 13. juni 1997 nr. 45 om allmennaksjeselskaper (allmennaksjeloven)."
    },
    {
        "tag": "table",
        "class": "listeItem avsnitt",
        "html": "<tr><td data-level=\"1\" class=\"morTag_nf small leftMargin_1 listeitemNummer morTableVerticalAlignTop morTableAlignRight morTableWidthPercent5\">3\t</td><td class=\" morTableVerticalAlignTop morTableAlignLeft\"><a data-id=\"lov/2019-03-15-6\" class=\" reference\" href=\"/lov/2019-03-15-6\">Lov 15. mars 2019 nr. 6 om verdipapirsentraler og verdipapiroppgjør mv. (verdipapirsentralloven)</a>.</td></tr>",
        "text": "3\tLov 15. mars 2019 nr. 6 om verdipapirsentraler og verdipapiroppgjør mv. (verdipapirsentralloven)."
    },
    {
        "tag": "h2",
        "class": "",
        "html": "I",
        "text": "I"
    },
    {
        "tag": "p",
        "class": "avsnitt",
        "html": "I <a data-id=\"lov/1997-06-13-44\" class=\" reference\" href=\"/lov/1997-06-13-44\">lov 13. juni 1997 nr. 44 om aksjeselskaper</a> gjøres følgende endringer:",
        "text": "I lov 13. juni 1997 nr. 44 om aksjeselskaper gjøres følgende endringer:"
    },
    {
        "tag": "p",
        "class": "avsnitt",
        "html": "<a data-id=\"lov/1997-06-13-44/§1-7\" class=\" reference\" href=\"/lov/1997-06-13-44/%C2%A71-7\">§ 1-7</a> nytt tredje ledd skal lyde:",
        "text": "§ 1-7 nytt tredje ledd skal lyde:"
    },
    {
        "tag": "table",
        "class": "numeral avsnitt",
        "html": "<tr><td class=\"morTableVerticalAlignTop morTableAlignLeft \"><span class=\"avsnittNummer numeral\">(3)</span> For meldinger mv. mellom selskapet og eiere av forvalterregistrerte aksjer gjelder <a data-id=\"lov/1997-06-13-45/§1-8\" class=\" reference\" href=\"/lov/1997-06-13-45/%C2%A71-8\">allmennaksjeloven § 1-8</a>.</td></tr>",
        "text": "(3) For meldinger mv. mellom selskapet og eiere av forvalterregistrerte aksjer gjelder allmennaksjeloven § 1-8."
    },
    {
        "tag": "p",
        "class": "avsnitt",
        "html": "Nåværende tredje ledd blir nytt fjerde ledd.",
        "text": "Nåværende tredje ledd blir nytt fjerde ledd."
    },
    {
        "tag": "p",
        "class": "avsnitt",
        "html": "<a data-id=\"lov/1997-06-13-44/§4-4\" class=\" reference\" href=\"/lov/1997-06-13-44/%C2%A74-4\">§ 4-4</a> skal lyde:",
        "text": "§ 4-4 skal lyde:"
    },
    null,
    null,
    {
        "tag": "span",
        "class": "paragrafValue",
        "html": "§ 4-4.",
        "text": "§ 4-4."
    },
    {
        "tag": "span",
        "class": "paragrafTittel",
        "html": "<em class=\" \">Registrering av aksjer i en verdipapirsentral</em>",
        "text": "Registrering av aksjer i en verdipapirsentral"
    },
    {
        "tag": "table",
        "class": "numeral avsnitt",
        "html": "<tr><td class=\"morTableVerticalAlignTop morTableAlignLeft \"><span class=\"avsnittNummer numeral\">(1)</span> Det kan bestemmes i vedtektene at selskapets aksjer skal registreres i en verdipapirsentral som har tillatelse etter eller er anerkjent etter verdipapirsentralforordningen (forordning <a data-id=\"eu/32014r0909\" class=\" reference\" href=\"/eu/32014r0909\">(EU) 909/2014</a>). Det skal i så fall også fastsettes i vedtektene i hvilken verdipapirsentral aksjene blir registrert.</td></tr>",
        "text": "(1) Det kan bestemmes i vedtektene at selskapets aksjer skal registreres i en verdipapirsentral som har tillatelse etter eller er anerkjent etter verdipapirsentralforordningen (forordning (EU) 909/2014). Det skal i så fall også fastsettes i vedtektene i hvilken verdipapirsentral aksjene blir registrert."
    },
    {
        "tag": "table",
        "class": "numeral avsnitt",
        "html": "<tr><td class=\"morTableVerticalAlignTop morTableAlignLeft \"><span class=\"avsnittNummer numeral\">(2)</span> Er selskapets aksjer registrert i en verdipapirsentral, gjelder <a data-id=\"lov/1997-06-13-45\" class=\" reference\" href=\"/lov/1997-06-13-45\">allmennaksjelovens</a> regler om slik registrering for aksjene, herunder <a data-id=\"lov/1997-06-13-45/§4-10\" class=\" reference\" href=\"/lov/1997-06-13-45/%C2%A74-10\">§ 4-10</a> om forvalterregistrering. Det samme gjelder <a data-id=\"lov/1997-06-13-45/§4-5\" class=\" reference\" href=\"/lov/1997-06-13-45/%C2%A74-5\">allmennaksjeloven § 4-5</a> om offentlighet om aksjeeiere, likevel slik at <a data-id=\"lov/1997-06-13-45/§4-5\" class=\" reference\" href=\"/lov/1997-06-13-45/%C2%A74-5\">allmennaksjeloven § 4-5</a> annet, tredje og femte ledd bare gjelder for selskaper med forvalterregistrerte aksjer.</td></tr>",
        "text": "(2) Er selskapets aksjer registrert i en verdipapirsentral, gjelder allmennaksjelovens regler om slik registrering for aksjene, herunder § 4-10 om forvalterregistrering. Det samme gjelder allmennaksjeloven § 4-5 om offentlighet om aksjeeiere, likevel slik at allmennaksjeloven § 4-5 annet, tredje og femte ledd bare gjelder for selskaper med forvalterregistrerte aksjer."
    },
    {
        "tag": "table",
        "class": "numeral avsnitt",
        "html": "<tr><td class=\"morTableVerticalAlignTop morTableAlignLeft \"><span class=\"avsnittNummer numeral\">(3)</span> For gjennomføring av generalforsamling i selskaper med aksjer registrert i en verdipapirsentral gjelder følgende særregler:</td></tr>",
        "text": "(3) For gjennomføring av generalforsamling i selskaper med aksjer registrert i en verdipapirsentral gjelder følgende særregler:"
    },
    {
        "tag": "table",
        "class": "listeItem avsnitt",
        "html": "<tr><td data-level=\"1\" class=\"morTag_n leftMargin_1 listeitemNummer morTableVerticalAlignTop morTableAlignRight morTableWidthPercent5\">a)\t</td><td class=\" morTableVerticalAlignTop morTableAlignLeft\">Reglene om registreringsdato i <a data-id=\"lov/1997-06-13-45/§5-2\" class=\" reference\" href=\"/lov/1997-06-13-45/%C2%A75-2\">allmennaksjeloven § 5-2</a> første ledd gjelder tilsvarende.</td></tr>",
        "text": "a)\tReglene om registreringsdato i allmennaksjeloven § 5-2 første ledd gjelder tilsvarende."
    },
    {
        "tag": "table",
        "class": "listeItem avsnitt",
        "html": "<tr><td data-level=\"1\" class=\"morTag_n leftMargin_1 listeitemNummer morTableVerticalAlignTop morTableAlignRight morTableWidthPercent5\">b)\t</td><td class=\" morTableVerticalAlignTop morTableAlignLeft\">Reglene om forhåndsmelding til selskapet for å delta på generalforsamlingen i <a data-id=\"lov/1997-06-13-45/§5-3\" class=\" reference\" href=\"/lov/1997-06-13-45/%C2%A75-3\">allmennaksjeloven § 5-3</a> gjelder tilsvarende.</td></tr>",
        "text": "b)\tReglene om forhåndsmelding til selskapet for å delta på generalforsamlingen i allmennaksjeloven § 5-3 gjelder tilsvarende."
    },
    {
        "tag": "table",
        "class": "listeItem avsnitt",
        "html": "<tr><td data-level=\"1\" class=\"morTag_n leftMargin_1 listeitemNummer morTableVerticalAlignTop morTableAlignRight morTableWidthPercent5\">c)\t</td><td class=\" morTableVerticalAlignTop morTableAlignLeft\">Innkallingen til generalforsamlingen skal opplyse om tidspunktet for registreringsdato og frist for forhåndsmelding i samsvar med bestemmelsene i <a data-id=\"lov/1997-06-13-45/§5-10\" class=\" reference\" href=\"/lov/1997-06-13-45/%C2%A75-10\">allmennaksjeloven § 5-10</a> første ledd tredje og fjerde punktum.</td></tr>",
        "text": "c)\tInnkallingen til generalforsamlingen skal opplyse om tidspunktet for registreringsdato og frist for forhåndsmelding i samsvar med bestemmelsene i allmennaksjeloven § 5-10 første ledd tredje og fjerde punktum."
    },
    {
        "tag": "table",
        "class": "listeItem avsnitt",
        "html": "<tr><td data-level=\"1\" class=\"morTag_n leftMargin_1 listeitemNummer morTableVerticalAlignTop morTableAlignRight morTableWidthPercent5\">d)\t</td><td class=\" morTableVerticalAlignTop morTableAlignLeft\">Innkallingen til generalforsamlingen skal være sendt senest to uker før møtet skal holdes, om ikke vedtektene setter en lengre frist.</td></tr>",
        "text": "d)\tInnkallingen til generalforsamlingen skal være sendt senest to uker før møtet skal holdes, om ikke vedtektene setter en lengre frist."
    },
    {
        "tag": "p",
        "class": "marg",
        "html": "Første punktum bokstav c og d kan fravikes etter reglene om forenklet generalforsamlingsbehandling, jf. <a data-id=\"lov/1997-06-13-44/§5-7\" class=\" reference\" href=\"/lov/1997-06-13-44/%C2%A75-7\">§ 5-7</a>.",
        "text": "Første punktum bokstav c og d kan fravikes etter reglene om forenklet generalforsamlingsbehandling, jf. § 5-7."
    },
    {
        "tag": "p",
        "class": "avsnitt",
        "html": "<a data-id=\"lov/1997-06-13-44/§4-5\" class=\" reference\" href=\"/lov/1997-06-13-44/%C2%A74-5\">§ 4-5</a> annet ledd skal lyde:",
        "text": "§ 4-5 annet ledd skal lyde:"
    },
    {
        "tag": "table",
        "class": "numeral avsnitt",
        "html": "<tr><td class=\"morTableVerticalAlignTop morTableAlignLeft \"><span class=\"avsnittNummer numeral\">(2)</span> I aksjeeierboken skal aksjeeierne innføres i alfabetisk orden med angivelse av navn, fødselsdato, digital adresse og bostedsadresse, eller – for juridiske personer – foretaksnavn, organisasjonsnummer eller lignende identifikasjonsnummer, digital adresse, forretningsadresse og eventuelt postadresse.</td></tr>",
        "text": "(2) I aksjeeierboken skal aksjeeierne innføres i alfabetisk orden med angivelse av navn, fødselsdato, digital adresse og bostedsadresse, eller – for juridiske personer – foretaksnavn, organisasjonsnummer eller lignende identifikasjonsnummer, digital adresse, forretningsadresse og eventuelt postadresse."
    },
    {
        "tag": "h2",
        "class": "",
        "html": "II",
        "text": "II"
    },
    {
        "tag": "p",
        "class": "avsnitt",
        "html": "I <a data-id=\"lov/1997-06-13-45\" class=\" reference\" href=\"/lov/1997-06-13-45\">lov 13. juni 1997 nr. 45 om allmennaksjeselskaper</a> gjøres følgende endringer:",
        "text": "I lov 13. juni 1997 nr. 45 om allmennaksjeselskaper gjøres følgende endringer:"
    },
    {
        "tag": "p",
        "class": "avsnitt",
        "html": "Overskriften til avsnitt III i <a data-id=\"lov/1997-06-13-45/kap1\" class=\" reference\" href=\"/lov/1997-06-13-45/kap1\">kapittel 1</a> skal lyde:",
        "text": "Overskriften til avsnitt III i kapittel 1 skal lyde:"
    },
    {
        "tag": "h3",
        "class": "",
        "html": "III. Utarbeidelse og oppbevaring av dokumentasjon, meldinger mv.",
        "text": "III. Utarbeidelse og oppbevaring av dokumentasjon, meldinger mv."
    },
    {
        "tag": "p",
        "class": "avsnitt",
        "html": "I avsnitt III skal nye <a data-id=\"lov/1997-06-13-45/§1-7\" class=\" reference\" href=\"/lov/1997-06-13-45/%C2%A71-7\">§ 1-7</a> og <a data-id=\"lov/1997-06-13-45/§1-8\" class=\" reference\" href=\"/lov/1997-06-13-45/%C2%A71-8\">§ 1-8</a> lyde:",
        "text": "I avsnitt III skal nye § 1-7 og § 1-8 lyde:"
    },
    null,
    null,
    {
        "tag": "span",
        "class": "paragrafValue",
        "html": "§ 1-7.",
        "text": "§ 1-7."
    },
    {
        "tag": "span",
        "class": "paragrafTittel",
        "html": "<em class=\" \">Meldinger mv.</em>",
        "text": "Meldinger mv."
    },
    {
        "tag": "table",
        "class": "numeral avsnitt",
        "html": "<tr><td class=\"morTableVerticalAlignTop morTableAlignLeft \"><span class=\"avsnittNummer numeral\">(1)</span> Selskapets meldinger mv. til aksjeeierne etter denne loven gis på den måten styret bestemmer. Styret skal informere aksjeeierne i rimelig tid før ny kommunikasjonsmåte tas i bruk. Meldinger mv. skal gis på en betryggende og hensiktsmessig måte.</td></tr>",
        "text": "(1) Selskapets meldinger mv. til aksjeeierne etter denne loven gis på den måten styret bestemmer. Styret skal informere aksjeeierne i rimelig tid før ny kommunikasjonsmåte tas i bruk. Meldinger mv. skal gis på en betryggende og hensiktsmessig måte."
    },
    {
        "tag": "table",
        "class": "numeral avsnitt",
        "html": "<tr><td class=\"morTableVerticalAlignTop morTableAlignLeft \"><span class=\"avsnittNummer numeral\">(2)</span> Aksjeeiernes meldinger mv. til selskapet etter denne loven kan alltid sendes til selskapets forretningsadresse, og til digital adresse og postadresse som selskapet har oppgitt.</td></tr>",
        "text": "(2) Aksjeeiernes meldinger mv. til selskapet etter denne loven kan alltid sendes til selskapets forretningsadresse, og til digital adresse og postadresse som selskapet har oppgitt."
    },
    {
        "tag": "table",
        "class": "numeral avsnitt",
        "html": "<tr><td class=\"morTableVerticalAlignTop morTableAlignLeft \"><span class=\"avsnittNummer numeral\">(3)</span> Departementet kan i forskrift gi nærmere bestemmelser om krav til meldinger mv. mellom selskapet og aksjeeierne.</td></tr>",
        "text": "(3) Departementet kan i forskrift gi nærmere bestemmelser om krav til meldinger mv. mellom selskapet og aksjeeierne."
    },
    null,
    null,
    {
        "tag": "span",
        "class": "paragrafValue",
        "html": "§ 1-8.",
        "text": "§ 1-8."
    },
    {
        "tag": "span",
        "class": "paragrafTittel",
        "html": "<em class=\" \">Meldinger mv. til eiere av forvalterregistrerte aksjer</em>",
        "text": "Meldinger mv. til eiere av forvalterregistrerte aksjer"
    },
    {
        "tag": "table",
        "class": "numeral avsnitt",
        "html": "<tr><td class=\"morTableVerticalAlignTop morTableAlignLeft \"><span class=\"avsnittNummer numeral\">(1)</span> Selskapets meldinger mv. til eiere av forvalterregistrerte aksjer etter denne loven skal sendes forvalteren. Dette gjelder ikke dersom meldingen er sendt direkte til slik eier. Tredjepersoner som etter denne loven plikter å sende melding mv. til eiere av forvalterregistrerte aksjer, kan kreve at selskapet bistår med dette.</td></tr>",
        "text": "(1) Selskapets meldinger mv. til eiere av forvalterregistrerte aksjer etter denne loven skal sendes forvalteren. Dette gjelder ikke dersom meldingen er sendt direkte til slik eier. Tredjepersoner som etter denne loven plikter å sende melding mv. til eiere av forvalterregistrerte aksjer, kan kreve at selskapet bistår med dette."
    },
    {
        "tag": "table",
        "class": "numeral avsnitt",
        "html": "<tr><td class=\"morTableVerticalAlignTop morTableAlignLeft \"><span class=\"avsnittNummer numeral\">(2)</span> Forvaltere og andre formidlere som definert i <a data-id=\"lov/2019-03-15-6/§4-5\" class=\" reference\" href=\"/lov/2019-03-15-6/%C2%A74-5\">verdipapirsentralloven § 4-5</a> første ledd, skal uten opphold videreformidle meldinger mv. mellom selskapet og eiere av forvalterregistrerte aksjer.</td></tr>",
        "text": "(2) Forvaltere og andre formidlere som definert i verdipapirsentralloven § 4-5 første ledd, skal uten opphold videreformidle meldinger mv. mellom selskapet og eiere av forvalterregistrerte aksjer."
    },
    {
        "tag": "table",
        "class": "numeral avsnitt",
        "html": "<tr><td class=\"morTableVerticalAlignTop morTableAlignLeft \"><span class=\"avsnittNummer numeral\">(3)</span> Departementet kan i forskrift gi nærmere bestemmelser om krav til meldinger mv. mellom selskapet og eiere av forvalterregistrerte aksjer, herunder om format og tidsfrister, samt om videreformidling av meldinger mv. etter annet ledd.</td></tr>",
        "text": "(3) Departementet kan i forskrift gi nærmere bestemmelser om krav til meldinger mv. mellom selskapet og eiere av forvalterregistrerte aksjer, herunder om format og tidsfrister, samt om videreformidling av meldinger mv. etter annet ledd."
    },
    {
        "tag": "p",
        "class": "avsnitt",
        "html": "<a data-id=\"lov/1997-06-13-45/§4-2\" class=\" reference\" href=\"/lov/1997-06-13-45/%C2%A74-2\">§ 4-2</a> tredje ledd oppheves.",
        "text": "§ 4-2 tredje ledd oppheves."
    },
    {
        "tag": "p",
        "class": "avsnitt",
        "html": "<a data-id=\"lov/1997-06-13-45/§4-4\" class=\" reference\" href=\"/lov/1997-06-13-45/%C2%A74-4\">§ 4-4</a> annet ledd nr. 4 skal lyde:",
        "text": "§ 4-4 annet ledd nr. 4 skal lyde:"
    },
    {
        "tag": "table",
        "class": "listeItem avsnitt",
        "html": "<tr><td data-level=\"1\" class=\"morTag_n leftMargin_1 listeitemNummer morTableVerticalAlignTop morTableAlignRight morTableWidthPercent5\">4.\t</td><td class=\" morTableVerticalAlignTop morTableAlignLeft\">aksjeeiernes navn, fødselsdato, digital adresse og bostedsadresse, eller – for juridiske personer – foretaksnavn, organisasjonsnummer eller lignende identifikasjonsnummer, digital adresse, forretningsadresse og eventuelt postadresse;</td></tr>",
        "text": "4.\taksjeeiernes navn, fødselsdato, digital adresse og bostedsadresse, eller – for juridiske personer – foretaksnavn, organisasjonsnummer eller lignende identifikasjonsnummer, digital adresse, forretningsadresse og eventuelt postadresse;"
    },
    {
        "tag": "p",
        "class": "avsnitt",
        "html": "<a data-id=\"lov/1997-06-13-45/§4-4\" class=\" reference\" href=\"/lov/1997-06-13-45/%C2%A74-4\">§ 4-4</a> nytt tredje ledd skal lyde:",
        "text": "§ 4-4 nytt tredje ledd skal lyde:"
    },
    {
        "tag": "table",
        "class": "numeral avsnitt",
        "html": "<tr><td class=\"morTableVerticalAlignTop morTableAlignLeft \"><span class=\"avsnittNummer numeral\">(3)</span> Den som er innført i aksjeeierregisteret har rett til å kreve at ufullstendige eller uriktige opplysninger blir rettet.</td></tr>",
        "text": "(3) Den som er innført i aksjeeierregisteret har rett til å kreve at ufullstendige eller uriktige opplysninger blir rettet."
    },
    {
        "tag": "p",
        "class": "avsnitt",
        "html": "<a data-id=\"lov/1997-06-13-45/§4-5\" class=\" reference\" href=\"/lov/1997-06-13-45/%C2%A74-5\">§ 4-5</a> skal lyde:",
        "text": "§ 4-5 skal lyde:"
    },
    null,
    null,
    {
        "tag": "span",
        "class": "paragrafValue",
        "html": "§ 4-5.",
        "text": "§ 4-5."
    },
    {
        "tag": "span",
        "class": "paragrafTittel",
        "html": "<em class=\" \">Offentlighet om aksjeeiere</em>",
        "text": "Offentlighet om aksjeeiere"
    },
    {
        "tag": "table",
        "class": "numeral avsnitt",
        "html": "<tr><td class=\"morTableVerticalAlignTop morTableAlignLeft \"><span class=\"avsnittNummer numeral\">(1)</span> Aksjeeierregisteret skal være tilgjengelig for enhver. Dette gjelder likevel ikke opplysninger om digitale adresser.</td></tr>",
        "text": "(1) Aksjeeierregisteret skal være tilgjengelig for enhver. Dette gjelder likevel ikke opplysninger om digitale adresser."
    },
    {
        "tag": "table",
        "class": "numeral avsnitt",
        "html": "<tr><td class=\"morTableVerticalAlignTop morTableAlignLeft \"><span class=\"avsnittNummer numeral\">(2)</span> Enhver kan be selskapet om innsyn i hvem som er eiere av forvalterregistrerte aksjer i selskapet, og hvor mange aksjer hver enkelt eier. Selskapet kan kreve å få dekket sine faktiske kostnader i forbindelse med innsynskravet.</td></tr>",
        "text": "(2) Enhver kan be selskapet om innsyn i hvem som er eiere av forvalterregistrerte aksjer i selskapet, og hvor mange aksjer hver enkelt eier. Selskapet kan kreve å få dekket sine faktiske kostnader i forbindelse med innsynskravet."
    },
    {
        "tag": "table",
        "class": "numeral avsnitt",
        "html": "<tr><td class=\"morTableVerticalAlignTop morTableAlignLeft \"><span class=\"avsnittNummer numeral\">(3)</span> Selskapet skal oppbevare opplysninger om aksjeeiere som er innhentet for å oppfylle innsynsretten etter annet ledd, i ti år. Dersom en offentlig myndighet krever det, plikter selskapet å utlevere opplysningene.</td></tr>",
        "text": "(3) Selskapet skal oppbevare opplysninger om aksjeeiere som er innhentet for å oppfylle innsynsretten etter annet ledd, i ti år. Dersom en offentlig myndighet krever det, plikter selskapet å utlevere opplysningene."
    },
    {
        "tag": "table",
        "class": "numeral avsnitt",
        "html": "<tr><td class=\"morTableVerticalAlignTop morTableAlignLeft \"><span class=\"avsnittNummer numeral\">(4)</span> Departementet kan i forskrift gi nærmere bestemmelser om innsynsrett etter første og annet ledd, herunder om frist for å gi innsyn og om betaling av gebyr. Departementet kan i forskrift gi nærmere bestemmelser om oppbevaring av opplysninger etter tredje ledd.</td></tr>",
        "text": "(4) Departementet kan i forskrift gi nærmere bestemmelser om innsynsrett etter første og annet ledd, herunder om frist for å gi innsyn og om betaling av gebyr. Departementet kan i forskrift gi nærmere bestemmelser om oppbevaring av opplysninger etter tredje ledd."
    },
    {
        "tag": "table",
        "class": "numeral avsnitt",
        "html": "<tr><td class=\"morTableVerticalAlignTop morTableAlignLeft \"><span class=\"avsnittNummer numeral\">(5)</span> Departementet kan i forskrift gi nærmere bestemmelser om plikt for selskaper til periodisk å offentliggjøre en oversikt over aksjeeiere i selskapet som skal være kostnadsfritt tilgjengelig for allmennheten. I forskriften kan det blant annet gis regler om hvilke opplysninger som skal offentliggjøres, hvordan og hvor ofte disse skal offentliggjøres, varighet for offentliggjøringen, begrensninger i offentliggjøringsplikten, samt oppbevaring av opplysninger.</td></tr>",
        "text": "(5) Departementet kan i forskrift gi nærmere bestemmelser om plikt for selskaper til periodisk å offentliggjøre en oversikt over aksjeeiere i selskapet som skal være kostnadsfritt tilgjengelig for allmennheten. I forskriften kan det blant annet gis regler om hvilke opplysninger som skal offentliggjøres, hvordan og hvor ofte disse skal offentliggjøres, varighet for offentliggjøringen, begrensninger i offentliggjøringsplikten, samt oppbevaring av opplysninger."
    },
    {
        "tag": "p",
        "class": "avsnitt",
        "html": "<a data-id=\"lov/1997-06-13-45/§4-10\" class=\" reference\" href=\"/lov/1997-06-13-45/%C2%A74-10\">§ 4-10</a> skal lyde:",
        "text": "§ 4-10 skal lyde:"
    },
    null,
    null,
    {
        "tag": "span",
        "class": "paragrafValue",
        "html": "§ 4-10.",
        "text": "§ 4-10."
    },
    {
        "tag": "span",
        "class": "paragrafTittel",
        "html": "<em class=\" \">Forvalterregistrering</em>",
        "text": "Forvalterregistrering"
    },
    {
        "tag": "table",
        "class": "numeral avsnitt",
        "html": "<tr><td class=\"morTableVerticalAlignTop morTableAlignLeft \"><span class=\"avsnittNummer numeral\">(1)</span> En bank eller annen forvalter som er godkjent av Kongen, kan føres inn i aksjeeierregisteret i stedet for en utenlandsk aksjeeier når aksjene er tatt opp til handel på norsk regulert marked. Som utenlandsk aksjeeier regnes selskap registrert i utlandet, med mindre selskapets hovedkontor befinner seg her i riket, samt utenlandsk statsborger som ikke er bosatt her i riket. Kongen kan samtykke i forvalterregistrering av aksjer som tilhører utenlandske aksjeeiere også i andre tilfeller enn nevnt i første punktum. En annen verdipapirsentral kan etter forskrift gitt av Kongen opprette et delregister som føres inn i aksjeeierregisteret på vegne av aksjeeier. <a data-id=\"lov/1997-06-13-45/§4-5\" class=\" reference\" href=\"/lov/1997-06-13-45/%C2%A74-5\">§ 4-5</a> gjelder tilsvarende for delregisteret. Selskapet kan vedtektsfeste at aksjene i selskapet ikke skal kunne forvalterregistreres.</td></tr>",
        "text": "(1) En bank eller annen forvalter som er godkjent av Kongen, kan føres inn i aksjeeierregisteret i stedet for en utenlandsk aksjeeier når aksjene er tatt opp til handel på norsk regulert marked. Som utenlandsk aksjeeier regnes selskap registrert i utlandet, med mindre selskapets hovedkontor befinner seg her i riket, samt utenlandsk statsborger som ikke er bosatt her i riket. Kongen kan samtykke i forvalterregistrering av aksjer som tilhører utenlandske aksjeeiere også i andre tilfeller enn nevnt i første punktum. En annen verdipapirsentral kan etter forskrift gitt av Kongen opprette et delregister som føres inn i aksjeeierregisteret på vegne av aksjeeier. § 4-5 gjelder tilsvarende for delregisteret. Selskapet kan vedtektsfeste at aksjene i selskapet ikke skal kunne forvalterregistreres."
    },
    {
        "tag": "table",
        "class": "numeral avsnitt",
        "html": "<tr><td class=\"morTableVerticalAlignTop morTableAlignLeft \"><span class=\"avsnittNummer numeral\">(2)</span> Aksjeeierregisteret skal inneholde opplysninger om forvalterens navn, organisasjonsnummer eller lignende identifikasjonsnummer, digitale adresse, forretningsadresse og eventuelt postadresse og at denne er forvalter av aksjene. Det skal også fremgå hvor mange aksjer forvalteroppdraget til enhver tid omfatter.</td></tr>",
        "text": "(2) Aksjeeierregisteret skal inneholde opplysninger om forvalterens navn, organisasjonsnummer eller lignende identifikasjonsnummer, digitale adresse, forretningsadresse og eventuelt postadresse og at denne er forvalter av aksjene. Det skal også fremgå hvor mange aksjer forvalteroppdraget til enhver tid omfatter."
    },
    {
        "tag": "table",
        "class": "numeral avsnitt",
        "html": "<tr><td class=\"morTableVerticalAlignTop morTableAlignLeft \"><span class=\"avsnittNummer numeral\">(3)</span> En forvalter kan ikke utøve andre rettigheter i selskapet enn retten til å motta utbytte eller andre utdelinger på de aksjer forvalteroppdraget omfatter, herunder tildeling av nye aksjer ved kapitalforhøyelse. Forvalteren har fullmakt til å motta slike utdelinger.</td></tr>",
        "text": "(3) En forvalter kan ikke utøve andre rettigheter i selskapet enn retten til å motta utbytte eller andre utdelinger på de aksjer forvalteroppdraget omfatter, herunder tildeling av nye aksjer ved kapitalforhøyelse. Forvalteren har fullmakt til å motta slike utdelinger."
    },
    {
        "tag": "table",
        "class": "numeral avsnitt",
        "html": "<tr><td class=\"morTableVerticalAlignTop morTableAlignLeft \"><span class=\"avsnittNummer numeral\">(4)</span> Dersom selskapet eller en offentlig myndighet krever det, plikter forvalteren uten opphold å innhente og utlevere opplysninger om:</td></tr>",
        "text": "(4) Dersom selskapet eller en offentlig myndighet krever det, plikter forvalteren uten opphold å innhente og utlevere opplysninger om:"
    },
    {
        "tag": "table",
        "class": "listeItem avsnitt",
        "html": "<tr><td data-level=\"1\" class=\"morTag_n leftMargin_1 listeitemNummer morTableVerticalAlignTop morTableAlignRight morTableWidthPercent5\">a)\t</td><td class=\" morTableVerticalAlignTop morTableAlignLeft\">aksjeeiernes navn, digital adresse og bostedsadresse, eller – for juridiske personer – foretaksnavn, organisasjonsnummer eller lignende identifikasjonsnummer, digital adresse, forretningsadresse og eventuelt postadresse;</td></tr>",
        "text": "a)\taksjeeiernes navn, digital adresse og bostedsadresse, eller – for juridiske personer – foretaksnavn, organisasjonsnummer eller lignende identifikasjonsnummer, digital adresse, forretningsadresse og eventuelt postadresse;"
    },
    {
        "tag": "table",
        "class": "listeItem avsnitt",
        "html": "<tr><td data-level=\"1\" class=\"morTag_n leftMargin_1 listeitemNummer morTableVerticalAlignTop morTableAlignRight morTableWidthPercent5\">b)\t</td><td class=\" morTableVerticalAlignTop morTableAlignLeft\">antall aksjer som eies av den enkelte aksjeeier; og</td></tr>",
        "text": "b)\tantall aksjer som eies av den enkelte aksjeeier; og"
    },
    {
        "tag": "table",
        "class": "listeItem avsnitt",
        "html": "<tr><td data-level=\"1\" class=\"morTag_n leftMargin_1 listeitemNummer morTableVerticalAlignTop morTableAlignRight morTableWidthPercent5\">c)\t</td><td class=\" morTableVerticalAlignTop morTableAlignLeft\">i den utstrekning det anmodes om det, eventuell aksjeklasse og ervervsdato.</td></tr>",
        "text": "c)\ti den utstrekning det anmodes om det, eventuell aksjeklasse og ervervsdato."
    },
    {
        "tag": "p",
        "class": "marg",
        "html": "Dersom det er flere ledd med formidlere, skal anmodning og opplysninger etter første punktum videreformidles uten opphold mellom formidlerne. Selskapet og offentlige myndigheter kan i anmodningen kreve at opplysningene utleveres direkte av den formidleren som besitter opplysningene.",
        "text": "Dersom det er flere ledd med formidlere, skal anmodning og opplysninger etter første punktum videreformidles uten opphold mellom formidlerne. Selskapet og offentlige myndigheter kan i anmodningen kreve at opplysningene utleveres direkte av den formidleren som besitter opplysningene."
    },
    {
        "tag": "table",
        "class": "numeral avsnitt",
        "html": "<tr><td class=\"morTableVerticalAlignTop morTableAlignLeft \"><span class=\"avsnittNummer numeral\">(5)</span> Selskapet, forvaltere og formidlere kan oppbevare personopplysninger som er innhentet etter fjerde ledd, i inntil tolv måneder etter at de ble klar over at vedkommende ikke lenger er aksjeeier, med mindre annet følger av lov eller forskrift med hjemmel i lov. Aksjeeiere som er juridiske personer, kan kreve innsyn i opplysninger selskapet har innhentet etter fjerde ledd, og kan kreve at ufullstendige eller uriktige opplysninger blir rettet. For aksjeeiere som er fysiske personer, gjelder <a data-id=\"lov/2018-06-15-38\" class=\" reference\" href=\"/lov/2018-06-15-38\">personopplysningslovens</a> bestemmelser om innsyn og retting.</td></tr>",
        "text": "(5) Selskapet, forvaltere og formidlere kan oppbevare personopplysninger som er innhentet etter fjerde ledd, i inntil tolv måneder etter at de ble klar over at vedkommende ikke lenger er aksjeeier, med mindre annet følger av lov eller forskrift med hjemmel i lov. Aksjeeiere som er juridiske personer, kan kreve innsyn i opplysninger selskapet har innhentet etter fjerde ledd, og kan kreve at ufullstendige eller uriktige opplysninger blir rettet. For aksjeeiere som er fysiske personer, gjelder personopplysningslovens bestemmelser om innsyn og retting."
    },
    {
        "tag": "table",
        "class": "numeral avsnitt",
        "html": "<tr><td class=\"morTableVerticalAlignTop morTableAlignLeft \"><span class=\"avsnittNummer numeral\">(6)</span> Kongen kan gi forskrift om forvalterregistrering, herunder om forvalterens plikt til å gi selskapet og offentlig myndighet opplysning om eierforholdene til de aksjer som forvaltes, og plikt til å rapportere periodisk om eierforholdene til selskapet, offentlig myndighet eller til andre. Kongen kan i forskrift gi nærmere bestemmelser om formidleres plikter etter fjerde ledd, herunder format, tidsfrister og gebyr.</td></tr>",
        "text": "(6) Kongen kan gi forskrift om forvalterregistrering, herunder om forvalterens plikt til å gi selskapet og offentlig myndighet opplysning om eierforholdene til de aksjer som forvaltes, og plikt til å rapportere periodisk om eierforholdene til selskapet, offentlig myndighet eller til andre. Kongen kan i forskrift gi nærmere bestemmelser om formidleres plikter etter fjerde ledd, herunder format, tidsfrister og gebyr."
    },
    {
        "tag": "table",
        "class": "numeral avsnitt",
        "html": "<tr><td class=\"morTableVerticalAlignTop morTableAlignLeft \"><span class=\"avsnittNummer numeral\">(7)</span> Kongen kan i forskrift gi nærmere regler om tvangssalg av finansielle instrumenter registrert på en forvalterkonto der kontoen forvaltes av noen uten godkjennelse etter første ledd, eller der forvalteren ikke oppfyller sin plikt til å gi opplysninger etter fjerde ledd eller etter forskrift gitt i medhold av sjette ledd.</td></tr>",
        "text": "(7) Kongen kan i forskrift gi nærmere regler om tvangssalg av finansielle instrumenter registrert på en forvalterkonto der kontoen forvaltes av noen uten godkjennelse etter første ledd, eller der forvalteren ikke oppfyller sin plikt til å gi opplysninger etter fjerde ledd eller etter forskrift gitt i medhold av sjette ledd."
    },
    {
        "tag": "p",
        "class": "avsnitt",
        "html": "<a data-id=\"lov/1997-06-13-45/§4-15\" class=\" reference\" href=\"/lov/1997-06-13-45/%C2%A74-15\">§ 4-15</a> femte ledd skal lyde:",
        "text": "§ 4-15 femte ledd skal lyde:"
    },
    {
        "tag": "table",
        "class": "numeral avsnitt",
        "html": "<tr><td class=\"morTableVerticalAlignTop morTableAlignLeft \"><span class=\"avsnittNummer numeral\">(5)</span> Det kan ikke vedtektsfestes andre begrensninger i aksjeeiernes rett til å overdra aksjer i perioden fra registreringsdatoen etter <a data-id=\"lov/1997-06-13-45/§5-2\" class=\" reference\" href=\"/lov/1997-06-13-45/%C2%A75-2\">§ 5-2</a> første ledd og frem til generalforsamlingen enn det som gjelder ellers.</td></tr>",
        "text": "(5) Det kan ikke vedtektsfestes andre begrensninger i aksjeeiernes rett til å overdra aksjer i perioden fra registreringsdatoen etter § 5-2 første ledd og frem til generalforsamlingen enn det som gjelder ellers."
    },
    {
        "tag": "p",
        "class": "avsnitt",
        "html": "<a data-id=\"lov/1997-06-13-45/§5-2\" class=\" reference\" href=\"/lov/1997-06-13-45/%C2%A75-2\">§ 5-2</a> skal lyde:",
        "text": "§ 5-2 skal lyde:"
    },
    null,
    null,
    {
        "tag": "span",
        "class": "paragrafValue",
        "html": "§ 5-2.",
        "text": "§ 5-2."
    },
    {
        "tag": "span",
        "class": "paragrafTittel",
        "html": "<em class=\" \">Aksjeeiernes rett til å delta på generalforsamlingen. Fullmektig</em>",
        "text": "Aksjeeiernes rett til å delta på generalforsamlingen. Fullmektig"
    },
    {
        "tag": "table",
        "class": "numeral avsnitt",
        "html": "<tr><td class=\"morTableVerticalAlignTop morTableAlignLeft \"><span class=\"avsnittNummer numeral\">(1)</span> Bare den som er aksjeeier fem virkedager før generalforsamlingen (registreringsdatoen), har rett til å delta og stemme på generalforsamlingen.</td></tr>",
        "text": "(1) Bare den som er aksjeeier fem virkedager før generalforsamlingen (registreringsdatoen), har rett til å delta og stemme på generalforsamlingen."
    },
    {
        "tag": "table",
        "class": "numeral avsnitt",
        "html": "<tr><td class=\"morTableVerticalAlignTop morTableAlignLeft \"><span class=\"avsnittNummer numeral\">(2)</span> Aksjeeieren har rett til å delta selv eller ved fullmektig etter eget valg. Retten til å delta på generalforsamlingen kan ikke begrenses i vedtektene.</td></tr>",
        "text": "(2) Aksjeeieren har rett til å delta selv eller ved fullmektig etter eget valg. Retten til å delta på generalforsamlingen kan ikke begrenses i vedtektene."
    },
    {
        "tag": "table",
        "class": "numeral avsnitt",
        "html": "<tr><td class=\"morTableVerticalAlignTop morTableAlignLeft \"><span class=\"avsnittNummer numeral\">(3)</span> Fullmektigen skal legge frem skriftlig fullmakt. Fullmakten skal være signert og datert. Fullmakten anses å gjelde bare for førstkommende generalforsamling hvis det ikke går tydelig frem at noe annet er ment. Aksjeeieren kan når som helst kalle tilbake fullmakten. Første og annet punktum gjelder tilsvarende for tilbakekall av fullmakten.</td></tr>",
        "text": "(3) Fullmektigen skal legge frem skriftlig fullmakt. Fullmakten skal være signert og datert. Fullmakten anses å gjelde bare for førstkommende generalforsamling hvis det ikke går tydelig frem at noe annet er ment. Aksjeeieren kan når som helst kalle tilbake fullmakten. Første og annet punktum gjelder tilsvarende for tilbakekall av fullmakten."
    },
    {
        "tag": "table",
        "class": "numeral avsnitt",
        "html": "<tr><td class=\"morTableVerticalAlignTop morTableAlignLeft \"><span class=\"avsnittNummer numeral\">(4)</span> Aksjeeiere har rett til å delta med rådgiver, og kan gi talerett til én rådgiver.</td></tr>",
        "text": "(4) Aksjeeiere har rett til å delta med rådgiver, og kan gi talerett til én rådgiver."
    },
    {
        "tag": "p",
        "class": "avsnitt",
        "html": "<a data-id=\"lov/1997-06-13-45/§5-3\" class=\" reference\" href=\"/lov/1997-06-13-45/%C2%A75-3\">§ 5-3</a> skal lyde:",
        "text": "§ 5-3 skal lyde:"
    },
    null,
    null,
    {
        "tag": "span",
        "class": "paragrafValue",
        "html": "§ 5-3.",
        "text": "§ 5-3."
    },
    {
        "tag": "span",
        "class": "paragrafTittel",
        "html": "<em class=\" \">Forhåndsmelding til selskapet for å delta på generalforsamlingen</em>",
        "text": "Forhåndsmelding til selskapet for å delta på generalforsamlingen"
    },
    {
        "tag": "table",
        "class": "numeral avsnitt",
        "html": "<tr><td class=\"morTableVerticalAlignTop morTableAlignLeft \"><span class=\"avsnittNummer numeral\">(1)</span> Eiere av forvalterregistrerte aksjer som vil delta på generalforsamlingen, må gi selskapet melding om dette på forhånd. I vedtektene kan det fastsettes at også øvrige aksjeeiere som vil delta på generalforsamlingen, må gi selskapet slik melding.</td></tr>",
        "text": "(1) Eiere av forvalterregistrerte aksjer som vil delta på generalforsamlingen, må gi selskapet melding om dette på forhånd. I vedtektene kan det fastsettes at også øvrige aksjeeiere som vil delta på generalforsamlingen, må gi selskapet slik melding."
    },
    {
        "tag": "table",
        "class": "numeral avsnitt",
        "html": "<tr><td class=\"morTableVerticalAlignTop morTableAlignLeft \"><span class=\"avsnittNummer numeral\">(2)</span> Melding etter første ledd må være mottatt av selskapet senest to virkedager før generalforsamlingen. Styret kan, før det er sendt innkalling til generalforsamlingen, fastsette en senere frist for meldingen.</td></tr>",
        "text": "(2) Melding etter første ledd må være mottatt av selskapet senest to virkedager før generalforsamlingen. Styret kan, før det er sendt innkalling til generalforsamlingen, fastsette en senere frist for meldingen."
    },
    {
        "tag": "table",
        "class": "numeral avsnitt",
        "html": "<tr><td class=\"morTableVerticalAlignTop morTableAlignLeft \"><span class=\"avsnittNummer numeral\">(3)</span> Departementet kan i forskrift gi nærmere bestemmelser om melding etter første ledd, herunder krav til format og innhold.</td></tr>",
        "text": "(3) Departementet kan i forskrift gi nærmere bestemmelser om melding etter første ledd, herunder krav til format og innhold."
    },
    {
        "tag": "p",
        "class": "avsnitt",
        "html": "<a data-id=\"lov/1997-06-13-45/§5-10\" class=\" reference\" href=\"/lov/1997-06-13-45/%C2%A75-10\">§ 5-10</a> første ledd skal lyde:",
        "text": "§ 5-10 første ledd skal lyde:"
    },
    {
        "tag": "table",
        "class": "numeral avsnitt",
        "html": "<tr><td class=\"morTableVerticalAlignTop morTableAlignLeft \"><span class=\"avsnittNummer numeral\">(1)</span> Generalforsamlingen innkalles ved skriftlig henvendelse til alle aksjeeiere med kjent adresse. Innkallingen skal angi tid og sted for møtet. Det skal opplyses om tidspunktet for registreringsdato, jf. <a data-id=\"lov/1997-06-13-45/§5-2\" class=\" reference\" href=\"/lov/1997-06-13-45/%C2%A75-2\">§ 5-2</a> første ledd, og at det bare er de som er aksjeeiere på registreringsdatoen, som har rett til å delta og stemme på generalforsamlingen. Frist for forhåndsmelding etter <a data-id=\"lov/1997-06-13-45/§5-3\" class=\" reference\" href=\"/lov/1997-06-13-45/%C2%A75-3\">§ 5-3</a> skal fremgå av innkallingen. Selskapet kan ikke kreve noen form for godtgjøring for utsendelsen av innkallingen.</td></tr>",
        "text": "(1) Generalforsamlingen innkalles ved skriftlig henvendelse til alle aksjeeiere med kjent adresse. Innkallingen skal angi tid og sted for møtet. Det skal opplyses om tidspunktet for registreringsdato, jf. § 5-2 første ledd, og at det bare er de som er aksjeeiere på registreringsdatoen, som har rett til å delta og stemme på generalforsamlingen. Frist for forhåndsmelding etter § 5-3 skal fremgå av innkallingen. Selskapet kan ikke kreve noen form for godtgjøring for utsendelsen av innkallingen."
    },
    {
        "tag": "p",
        "class": "avsnitt",
        "html": "<a data-id=\"lov/1997-06-13-45/§5-10\" class=\" reference\" href=\"/lov/1997-06-13-45/%C2%A75-10\">§ 5-10</a> fjerde ledd tredje punktum oppheves.",
        "text": "§ 5-10 fjerde ledd tredje punktum oppheves."
    },
    {
        "tag": "p",
        "class": "avsnitt",
        "html": "<a data-id=\"lov/1997-06-13-45/§5-11b\" class=\" reference\" href=\"/lov/1997-06-13-45/%C2%A75-11b\">§ 5-11 b</a> skal lyde:",
        "text": "§ 5-11 b skal lyde:"
    },
    null,
    null,
    {
        "tag": "span",
        "class": "paragrafValue",
        "html": "§ 5-11 b.",
        "text": "§ 5-11 b."
    },
    {
        "tag": "span",
        "class": "paragrafTittel",
        "html": "<em class=\" \">Særregler om innkalling og informasjon til aksjeeierne om generalforsamlingen i selskaper med aksjer tatt opp til handel på regulert marked mv.</em>",
        "text": "Særregler om innkalling og informasjon til aksjeeierne om generalforsamlingen i selskaper med aksjer tatt opp til handel på regulert marked mv."
    },
    {
        "tag": "p",
        "class": "avsnitt",
        "html": "For selskaper med aksjer tatt opp til handel på regulert marked, jf. <a data-id=\"lov/2007-06-29-75/§2-7\" class=\" reference\" href=\"/lov/2007-06-29-75/%C2%A72-7\">verdipapirhandelloven § 2-7</a> fjerde ledd, som ligger i eller har virksomhet i EØS-området, gjelder følgende særregler:",
        "text": "For selskaper med aksjer tatt opp til handel på regulert marked, jf. verdipapirhandelloven § 2-7 fjerde ledd, som ligger i eller har virksomhet i EØS-området, gjelder følgende særregler:"
    },
    {
        "tag": "table",
        "class": "listeItem avsnitt",
        "html": "<tr><td data-level=\"1\" class=\"morTag_n leftMargin_1 listeitemNummer morTableVerticalAlignTop morTableAlignRight morTableWidthPercent5\">1.\t</td><td class=\" morTableVerticalAlignTop morTableAlignLeft\">Innkallingsfristen etter <a data-id=\"lov/1997-06-13-45/§5-10\" class=\" reference\" href=\"/lov/1997-06-13-45/%C2%A75-10\">§ 5-10</a> annet ledd første punktum er 21 dager, om ikke vedtektene setter en lengre frist, jf. likevel <a data-id=\"lov/2007-06-29-75/§6-17\" class=\" reference\" href=\"/lov/2007-06-29-75/%C2%A76-17\">verdipapirhandelloven § 6-17</a> sjette ledd.</td></tr>",
        "text": "1.\tInnkallingsfristen etter § 5-10 annet ledd første punktum er 21 dager, om ikke vedtektene setter en lengre frist, jf. likevel verdipapirhandelloven § 6-17 sjette ledd."
    },
    {
        "tag": "table",
        "class": "listeItem avsnitt",
        "html": "<tr><td data-level=\"1\" class=\"morTag_n leftMargin_1 listeitemNummer morTableVerticalAlignTop morTableAlignRight morTableWidthPercent5\">2.\t</td><td class=\" morTableVerticalAlignTop morTableAlignLeft\">Innkallingen skal i tillegg til kravene etter <a data-id=\"lov/1997-06-13-45/§5-10\" class=\" reference\" href=\"/lov/1997-06-13-45/%C2%A75-10\">§ 5-10</a> oppfylle kravene etter forskrift fastsatt av Kongen til gjennomføring av direktiv <a data-id=\"eu/32007l0036/a5\" class=\" reference\" href=\"/eu/32007l0036/a5\">2007/36/EF artikkel 5</a> nr. 3.</td></tr>",
        "text": "2.\tInnkallingen skal i tillegg til kravene etter § 5-10 oppfylle kravene etter forskrift fastsatt av Kongen til gjennomføring av direktiv 2007/36/EF artikkel 5 nr. 3."
    },
    {
        "tag": "table",
        "class": "listeItem avsnitt",
        "html": "<tr><td data-level=\"1\" class=\"morTag_n leftMargin_1 listeitemNummer morTableVerticalAlignTop morTableAlignRight morTableWidthPercent5\">3.\t</td><td class=\" morTableVerticalAlignTop morTableAlignLeft\">Informasjon og skjemaer som gjelder generalforsamlingen, skal være tilgjengelig for aksjeeierne på selskapets internettsider etter regler i forskrift fastsatt av Kongen til gjennomføring av direktiv <a data-id=\"eu/32007l0036/a5\" class=\" reference\" href=\"/eu/32007l0036/a5\">2007/36/EF artikkel 5</a> nr. 4 og <a data-id=\"eu/32007l0036/a14\" class=\" reference\" href=\"/eu/32007l0036/a14\">artikkel 14</a> nr. 2.</td></tr>",
        "text": "3.\tInformasjon og skjemaer som gjelder generalforsamlingen, skal være tilgjengelig for aksjeeierne på selskapets internettsider etter regler i forskrift fastsatt av Kongen til gjennomføring av direktiv 2007/36/EF artikkel 5 nr. 4 og artikkel 14 nr. 2."
    },
    {
        "tag": "table",
        "class": "listeItem avsnitt",
        "html": "<tr><td data-level=\"1\" class=\"morTag_n leftMargin_1 listeitemNummer morTableVerticalAlignTop morTableAlignRight morTableWidthPercent5\">4.\t</td><td class=\" morTableVerticalAlignTop morTableAlignLeft\">Selskapet skal innen 15 dager etter generalforsamlingen offentliggjøre fortegnelsen over aksjeeiere som har deltatt på generalforsamlingen, jf. <a data-id=\"lov/1997-06-13-45/§5-13\" class=\" reference\" href=\"/lov/1997-06-13-45/%C2%A75-13\">§ 5-13</a>, på sine internettsider. Departementet kan i forskrift gi nærmere bestemmelser om offentliggjøring av fortegnelsen.</td></tr>",
        "text": "4.\tSelskapet skal innen 15 dager etter generalforsamlingen offentliggjøre fortegnelsen over aksjeeiere som har deltatt på generalforsamlingen, jf. § 5-13, på sine internettsider. Departementet kan i forskrift gi nærmere bestemmelser om offentliggjøring av fortegnelsen."
    },
    {
        "tag": "p",
        "class": "avsnitt",
        "html": "<a data-id=\"lov/1997-06-13-45/§18-4\" class=\" reference\" href=\"/lov/1997-06-13-45/%C2%A718-4\">§ 18-4</a> første ledd nytt tredje punktum skal lyde:",
        "text": "§ 18-4 første ledd nytt tredje punktum skal lyde:"
    },
    {
        "tag": "p",
        "class": "avsnitt",
        "html": "For frister som regnes i virkedager, skal lørdag, helgedag eller dag som etter lovgivningen er likestilt med helgedag, ikke medregnes.",
        "text": "For frister som regnes i virkedager, skal lørdag, helgedag eller dag som etter lovgivningen er likestilt med helgedag, ikke medregnes."
    },
    {
        "tag": "p",
        "class": "avsnitt",
        "html": "<a data-id=\"lov/1997-06-13-45/§18-5\" class=\" reference\" href=\"/lov/1997-06-13-45/%C2%A718-5\">§ 18-5</a> oppheves.",
        "text": "§ 18-5 oppheves."
    },
    {
        "tag": "h2",
        "class": "",
        "html": "III",
        "text": "III"
    },
    {
        "tag": "p",
        "class": "avsnitt",
        "html": "I <a data-id=\"lov/2019-03-15-6\" class=\" reference\" href=\"/lov/2019-03-15-6\">lov 15. mars 2019 nr. 6 om verdipapirsentraler og verdipapiroppgjør mv.</a> gjøres følgende endringer:",
        "text": "I lov 15. mars 2019 nr. 6 om verdipapirsentraler og verdipapiroppgjør mv. gjøres følgende endringer:"
    },
    {
        "tag": "p",
        "class": "avsnitt",
        "html": "<a data-id=\"lov/2019-03-15-6/§4-4\" class=\" reference\" href=\"/lov/2019-03-15-6/%C2%A74-4\">§ 4-4</a> fjerde ledd skal lyde:",
        "text": "§ 4-4 fjerde ledd skal lyde:"
    },
    {
        "tag": "p",
        "class": "avsnitt",
        "html": "Forvalteren plikter å gi opplysninger om de reelle eierne i samme omfang og på samme måte som verdipapirsentralen plikter å gi opplysninger etter <a data-id=\"lov/2019-03-15-6/§8-3\" class=\" reference\" href=\"/lov/2019-03-15-6/%C2%A78-3\">§ 8-3</a> første ledd eller annen lov, herunder sørge for å innhente opplysninger om de reelle eierne der det er flere ledd med forvaltere eller andre formidlere.",
        "text": "Forvalteren plikter å gi opplysninger om de reelle eierne i samme omfang og på samme måte som verdipapirsentralen plikter å gi opplysninger etter § 8-3 første ledd eller annen lov, herunder sørge for å innhente opplysninger om de reelle eierne der det er flere ledd med forvaltere eller andre formidlere."
    },
    {
        "tag": "p",
        "class": "avsnitt",
        "html": "<a data-id=\"lov/2019-03-15-6/§4-4\" class=\" reference\" href=\"/lov/2019-03-15-6/%C2%A74-4\">§ 4-4</a> sjette ledd skal lyde:",
        "text": "§ 4-4 sjette ledd skal lyde:"
    },
    {
        "tag": "p",
        "class": "avsnitt",
        "html": "Departementet kan i forskrift gi nærmere regler om forvaltere og forvalterkontoer, herunder forvalternes opplysningsplikt, plikt til å oppbevare opplysninger, videreformidlingsplikt, formater, tidsfrister, gebyrer mv. og unntak fra taushetsplikt. Reglene om gebyr mv. kan omfatte begrensninger i adgangen til å ta gebyr og krav til offentliggjøring av hvilke gebyrer mv. forvalteren krever.",
        "text": "Departementet kan i forskrift gi nærmere regler om forvaltere og forvalterkontoer, herunder forvalternes opplysningsplikt, plikt til å oppbevare opplysninger, videreformidlingsplikt, formater, tidsfrister, gebyrer mv. og unntak fra taushetsplikt. Reglene om gebyr mv. kan omfatte begrensninger i adgangen til å ta gebyr og krav til offentliggjøring av hvilke gebyrer mv. forvalteren krever."
    },
    {
        "tag": "p",
        "class": "avsnitt",
        "html": "Ny <a data-id=\"lov/2019-03-15-6/§4-5\" class=\" reference\" href=\"/lov/2019-03-15-6/%C2%A74-5\">§ 4-5</a> skal lyde:",
        "text": "Ny § 4-5 skal lyde:"
    },
    null,
    null,
    {
        "tag": "span",
        "class": "paragrafValue",
        "html": "§ 4-5.",
        "text": "§ 4-5."
    },
    {
        "tag": "span",
        "class": "paragrafTittel",
        "html": "<em class=\" \">Formidler</em>",
        "text": "Formidler"
    },
    {
        "tag": "p",
        "class": "avsnitt",
        "html": "Med formidler i denne loven menes en person som yter tjenester i form av oppbevaring av aksjer, administrasjon av aksjer eller vedlikehold av verdipapirkontoer på vegne av aksjeeiere eller andre.",
        "text": "Med formidler i denne loven menes en person som yter tjenester i form av oppbevaring av aksjer, administrasjon av aksjer eller vedlikehold av verdipapirkontoer på vegne av aksjeeiere eller andre."
    },
    {
        "tag": "p",
        "class": "avsnitt",
        "html": "Formidlere plikter å formidle informasjon mellom aksjeeiere og utstedere.",
        "text": "Formidlere plikter å formidle informasjon mellom aksjeeiere og utstedere."
    },
    {
        "tag": "p",
        "class": "avsnitt",
        "html": "Departementet kan i forskrift gi regler om formidlere, herunder om virkeområde, oppbevaringsplikt, registreringsplikt, opplysnings- og videreformidlingsplikt, plikt til å tilrettelegge for utøvelse av aksjeeierrettigheter, formater, tidsfrister, gebyrer mv. og unntak fra taushetsplikt. Reglene om gebyr mv. kan omfatte begrensninger i adgangen til å ta gebyr og krav til offentliggjøring av hvilke gebyrer mv. formidleren krever.",
        "text": "Departementet kan i forskrift gi regler om formidlere, herunder om virkeområde, oppbevaringsplikt, registreringsplikt, opplysnings- og videreformidlingsplikt, plikt til å tilrettelegge for utøvelse av aksjeeierrettigheter, formater, tidsfrister, gebyrer mv. og unntak fra taushetsplikt. Reglene om gebyr mv. kan omfatte begrensninger i adgangen til å ta gebyr og krav til offentliggjøring av hvilke gebyrer mv. formidleren krever."
    },
    {
        "tag": "p",
        "class": "avsnitt",
        "html": "<a data-id=\"lov/2019-03-15-6/§11-5\" class=\" reference\" href=\"/lov/2019-03-15-6/%C2%A711-5\">§ 11-5</a> nytt tredje ledd skal lyde:",
        "text": "§ 11-5 nytt tredje ledd skal lyde:"
    },
    {
        "tag": "p",
        "class": "avsnitt",
        "html": "Finanstilsynet kan gi en forvalter eller annen formidler pålegg om retting dersom vedkommende opptrer i strid med lov, bestemmelser gitt med hjemmel i lov eller vilkår for tillatelse.",
        "text": "Finanstilsynet kan gi en forvalter eller annen formidler pålegg om retting dersom vedkommende opptrer i strid med lov, bestemmelser gitt med hjemmel i lov eller vilkår for tillatelse."
    },
    {
        "tag": "p",
        "class": "avsnitt",
        "html": "Nåværende <a data-id=\"lov/2019-03-15-6/§11-5\" class=\" reference\" href=\"/lov/2019-03-15-6/%C2%A711-5\">§ 11-5</a> tredje ledd blir nytt fjerde ledd.",
        "text": "Nåværende § 11-5 tredje ledd blir nytt fjerde ledd."
    },
    {
        "tag": "p",
        "class": "avsnitt",
        "html": "<a data-id=\"lov/2019-03-15-6/§11-9\" class=\" reference\" href=\"/lov/2019-03-15-6/%C2%A711-9\">§ 11-9</a> første ledd tredje punktum skal lyde:",
        "text": "§ 11-9 første ledd tredje punktum skal lyde:"
    },
    {
        "tag": "p",
        "class": "avsnitt",
        "html": "Finanstilsynet kan også ilegge overtredelsesgebyr ved overtredelse av <a data-id=\"lov/2019-03-15-6/§2-1\" class=\" reference\" href=\"/lov/2019-03-15-6/%C2%A72-1\">§ 2-1</a>, <a data-id=\"lov/2019-03-15-6/§3-2\" class=\" reference\" href=\"/lov/2019-03-15-6/%C2%A73-2\">§ 3-2</a> første ledd, <a data-id=\"lov/2019-03-15-6/§3-3\" class=\" reference\" href=\"/lov/2019-03-15-6/%C2%A73-3\">§ 3-3</a> annet ledd, <a data-id=\"lov/2019-03-15-6/§4-1\" class=\" reference\" href=\"/lov/2019-03-15-6/%C2%A74-1\">§ 4-1</a>, <a data-id=\"lov/2019-03-15-6/§4-2\" class=\" reference\" href=\"/lov/2019-03-15-6/%C2%A74-2\">§ 4-2</a>, <a data-id=\"lov/2019-03-15-6/§4-3\" class=\" reference\" href=\"/lov/2019-03-15-6/%C2%A74-3\">§ 4-3</a> første og annet ledd, <a data-id=\"lov/2019-03-15-6/§4-4\" class=\" reference\" href=\"/lov/2019-03-15-6/%C2%A74-4\">§ 4-4</a> første til femte ledd, § 4-5, <a data-id=\"lov/2019-03-15-6/kap5\" class=\" reference\" href=\"/lov/2019-03-15-6/kap5\">kapittel 5</a>, <a data-id=\"lov/2019-03-15-6/kap6\" class=\" reference\" href=\"/lov/2019-03-15-6/kap6\">kapittel 6</a>, <a data-id=\"lov/2019-03-15-6/§10-1\" class=\" reference\" href=\"/lov/2019-03-15-6/%C2%A710-1\">§ 10-1</a> første ledd, <a data-id=\"lov/2019-03-15-6/§10-2\" class=\" reference\" href=\"/lov/2019-03-15-6/%C2%A710-2\">§ 10-2</a> eller §<a data-id=\"lov/2019-03-15-6/§11-3\" class=\" reference\" href=\"/lov/2019-03-15-6/%C2%A711-3\">§ 11-3</a> til <a data-id=\"lov/2019-03-15-6/§11-5\" class=\" reference\" href=\"/lov/2019-03-15-6/%C2%A711-5\">11-5</a> eller forskrifter gitt i medhold av disse bestemmelsene.",
        "text": "Finanstilsynet kan også ilegge overtredelsesgebyr ved overtredelse av § 2-1, § 3-2 første ledd, § 3-3 annet ledd, § 4-1, § 4-2, § 4-3 første og annet ledd, § 4-4 første til femte ledd, § 4-5, kapittel 5, kapittel 6, § 10-1 første ledd, § 10-2 eller §§ 11-3 til 11-5 eller forskrifter gitt i medhold av disse bestemmelsene."
    },
    {
        "tag": "h2",
        "class": "",
        "html": "IV",
        "text": "IV"
    },
    {
        "tag": "table",
        "class": "listeItem avsnitt",
        "html": "<tr><td data-level=\"1\" class=\"morTag_n leftMargin_1 listeitemNummer morTableVerticalAlignTop morTableAlignRight morTableWidthPercent5\">1.\t</td><td class=\" morTableVerticalAlignTop morTableAlignLeft\">Loven gjelder fra den tid Kongen bestemmer. Kongen kan sette i kraft de enkelte bestemmelser til forskjellig tid.</td></tr>",
        "text": "1.\tLoven gjelder fra den tid Kongen bestemmer. Kongen kan sette i kraft de enkelte bestemmelser til forskjellig tid."
    },
    {
        "tag": "table",
        "class": "listeItem avsnitt",
        "html": "<tr><td data-level=\"1\" class=\"morTag_n leftMargin_1 listeitemNummer morTableVerticalAlignTop morTableAlignRight morTableWidthPercent5\">2.\t</td><td class=\" morTableVerticalAlignTop morTableAlignLeft\">Departementet kan gi nærmere overgangsbestemmelser.</td></tr>",
        "text": "2.\tDepartementet kan gi nærmere overgangsbestemmelser."
    }
]