<?xml version="1.0" encoding="UTF-8"?>
<dokument xmlns:xsi="http://www.w3.org/2001/XMLSchema-instance" xmlns="https://lovdata.no/regelverk" xsi:schemaLocation="lov-eksempel.xsd" id="for-2017-06-26-977" type="lt" url="https://lovdata.no/lovtidend/forskrift/2017-06-26-977">
  <metadata>
    <type>lt</type>
    <base>LT</base>
    <id>LT/lt/2017-06-26-977</id>
    <dato>26.06.2017 nr. 977</dato>
    <dato type="iso">2017-06-26</dato>
    <ikraft>26.06.2017</ikraft>
    <ikraft type="iso">2017-06-26</ikraft>
    <departement>Helse- og omsorgsdepartementet</departement>
    <etat/>
    <gjelder>Norge</gjelder>
    <hjemmel/>
    <endrer type="ref">https://lovdata.no/for/2016-12-19-1732</endrer>
    <rettet/>
    <journalnummer>2017-0730</journalnummer>
  </metadata>
  <tekst>
    <korttittel>Endr. i forskrift om tilleggskrav for autorisasjon for helsepersonell</korttittel>
    <tittel>Forskrift om endring i forskrift om tilleggskrav for autorisasjon for helsepersonell med yrkeskvalifikasjoner fra land utenfor EØS og Sveits</tittel>
    <marg niv="1" id="/marg/1"><b>Hjemmel:</b> Fastsatt av Helse- og omsorgsdepartementet 26. juni 2017 med hjemmel i lov 2. juli 1999 nr. 64 om helsepersonell m.v. (helsepersonelloven) § 48a tredje ledd.</marg>
    <kapittel type="kapittel" id="/kapittel/i" url="https://lovdata.no/lovtidend/forskrift/2017-06-26-977/ki">
      <kverdi>I</kverdi>
      <ktittel/>
      <ledd id="/kapittel/i/ledd/1">I forskrift 19. desember 2016 nr. 1732 om tilleggskrav for autorisasjon for helsepersonell med yrkeskvalifikasjoner fra land utenfor EØS og Sveits gjøres følgende endring:
<br/></ledd>
      <ledd id="/kapittel/i/ledd/2">§ 11 skal lyde:</ledd>
      <ledd id="/kapittel/i/ledd/3">Forskriften, med unntak av vilkåret i § 4 om bestått fagprøve for å få autorisasjon som tannlege, trer i kraft 1. januar 2017. Fra samme tidspunkt oppheves forskrift 24. februar 2004 nr. 460 om tilleggskrav for autorisasjon for helsepersonell. Vilkåret i § 4 om bestått fagprøve for å få autorisasjon som tannlege trer i kraft 1. juli 2017.</ledd>
    </kapittel>
    <kapittel type="kapittel" id="/kapittel/ii" url="https://lovdata.no/lovtidend/forskrift/2017-06-26-977/kii">
      <kverdi>II</kverdi>
      <ktittel/>
      <ledd id="/kapittel/ii/ledd/1">Forskriften trer i kraft straks.</ledd>
    </kapittel>
  </tekst>
</dokument>
