<?xml version="1.0" encoding="UTF-8"?>
<dokument xmlns:xsi="http://www.w3.org/2001/XMLSchema-instance" xmlns="https://lovdata.no/regelverk" xsi:schemaLocation="lov-eksempel.xsd" id="for-2014-12-12-1585" type="lt" url="https://lovdata.no/lovtidend/forskrift/2014-12-12-1585">
  <metadata>
    <type>lt</type>
    <base>LT</base>
    <id>LT/lt/2014-12-12-1585</id>
    <dato>12.12.2014 nr. 1585</dato>
    <dato type="iso">2014-12-12</dato>
    <publisert>I 2014 hefte 16 s 2631</publisert>
    <ikraft>01.01.2015</ikraft>
    <ikraft type="iso">2015-01-01</ikraft>
    <departement>Arbeids- og sosialdepartementet</departement>
    <etat/>
    <gjelder>Norge</gjelder>
    <hjemmel/>
    <endrer type="ref">https://lovdata.no/for/2013-12-06-148</endrer>
    <rettet/>
    <journalnummer>2014-1188</journalnummer>
  </metadata>
  <tekst>
    <korttittel>Forskrift om medlemspremie i pensjonstrygden for fiskere, 2015</korttittel>
    <korttittel>3 Forskrift om medlemspremie i pensjonstrygden for fiskere for 2015 (Nr. 1585)</korttittel>
    <tittel>Forskrift om medlemspremie i pensjonstrygden for fiskere for 2015</tittel>
    <marg niv="1" id="/marg/1"><b>Hjemmel:</b> Fastsatt ved kgl.res. 12. desember 2014 med hjemmel i lov 28. juni 1957 nr. 12 om pensjonstrygd for fiskere § 16 nr. 1. Fremmet av Arbeids- og sosialdepartementet.</marg>
    <kapittel type="kapittel" id="/kapittel/i" url="https://lovdata.no/lovtidend/forskrift/2014-12-12-1585/ki">
      <kverdi>I</kverdi>
      <ktittel/>
      <ledd id="/kapittel/i/ledd/1">Årlig premie i pensjonstrygden for fiskere for pliktige medlemmer etter loven § 1 og frivillige medlemmer etter loven § 3 nr. 2 skal være 6 536 kroner for 2015. Ukespremie for frivillige medlemmer som er omfattet av loven § 3 nr. 1 skal være 125 kroner.</ledd>
    </kapittel>
    <kapittel type="kapittel" id="/kapittel/ii" url="https://lovdata.no/lovtidend/forskrift/2014-12-12-1585/kii">
      <kverdi>II</kverdi>
      <ktittel/>
      <ledd id="/kapittel/ii/ledd/1">Forskriften gjelder fra 1. januar 2015, likevel slik at fastsatt ukespremie skal gis virkning fra og med første hele premieuke i 2015.</ledd>
      <ledd id="/kapittel/ii/ledd/2">Fra samme tidspunkt oppheves forskrift 6. desember 2013 nr. 1408 om medlemspremie i pensjonstrygden for fiskere for 2014.</ledd>
    </kapittel>
  </tekst>
</dokument>
